{
  "__type__": "dragonBones.DragonBonesAsset",
  "_name": "chuangjianyouxi_ske",
  "_dragonBonesJson": "{\"frameRate\":24,\"armature\":[{\"slot\":[{\"color\":{},\"name\":\"btn_chuangjian\",\"parent\":\"按键\"},{\"z\":1,\"color\":{},\"name\":\"星光\",\"parent\":\"星光\"},{\"blendMode\":\"add\",\"z\":2,\"color\":{\"aM\":70},\"parent\":\"电光\",\"name\":\"电光\"},{\"blendMode\":\"add\",\"z\":3,\"color\":{\"aM\":70},\"parent\":\"电光1\",\"name\":\"电光1\"},{\"blendMode\":\"add\",\"z\":4,\"color\":{\"aM\":70},\"parent\":\"电光2\",\"name\":\"电光2\"},{\"blendMode\":\"add\",\"z\":5,\"color\":{\"aM\":70},\"parent\":\"电光21\",\"name\":\"电光21\"},{\"z\":6,\"color\":{},\"name\":\"星光1\",\"parent\":\"星光1\"}],\"defaultActions\":[{\"gotoAndPlay\":\"newAnimation\"}],\"type\":\"Armature\",\"frameRate\":24,\"skin\":[{\"name\":\"\",\"slot\":[{\"display\":[{\"path\":\"加入房间电光\",\"type\":\"image\",\"name\":\"加入房间电光\",\"transform\":{\"y\":-0.3077,\"x\":21.6606,\"skX\":-32.8074,\"skY\":-32.8074}}],\"blendMode\":\"add\",\"name\":\"电光21\"},{\"display\":[{\"path\":\"加入房间电光\",\"type\":\"image\",\"name\":\"加入房间电光\",\"transform\":{\"y\":-0.3077,\"x\":21.6606,\"skX\":-32.8074,\"skY\":-32.8074}}],\"blendMode\":\"add\",\"name\":\"电光2\"},{\"display\":[{\"path\":\"btn_chuangjian\",\"type\":\"image\",\"name\":\"btn_chuangjian\",\"transform\":{\"y\":6.7902,\"x\":2.25}}],\"name\":\"btn_chuangjian\"},{\"display\":[{\"path\":\"星光\",\"type\":\"image\",\"name\":\"星光\",\"transform\":{\"y\":-3.4467,\"x\":-0.2718}}],\"name\":\"星光\"},{\"display\":[{\"path\":\"加入房间电光\",\"type\":\"image\",\"name\":\"加入房间电光\",\"transform\":{\"y\":-0.3077,\"x\":21.6606,\"skX\":-32.8074,\"skY\":-32.8074}}],\"blendMode\":\"add\",\"name\":\"电光\"},{\"display\":[{\"path\":\"加入房间电光\",\"type\":\"image\",\"name\":\"加入房间电光\",\"transform\":{\"y\":-0.3077,\"x\":21.6606,\"skX\":-29.3846,\"skY\":-29.3846}}],\"blendMode\":\"add\",\"name\":\"电光1\"},{\"display\":[{\"path\":\"星光\",\"type\":\"image\",\"name\":\"星光\",\"transform\":{\"y\":-0.1791,\"x\":-0.3269}}],\"name\":\"星光1\"}]}],\"animation\":[{\"slot\":[{\"frame\":[{\"duration\":150,\"tweenEasing\":null}],\"name\":\"btn_chuangjian\"},{\"frame\":[{\"duration\":40,\"displayIndex\":-1,\"tweenEasing\":null},{\"duration\":15,\"curve\":[0.5,0,0.5,1],\"color\":{\"aM\":0}},{\"duration\":15,\"tweenEasing\":0,\"color\":{\"aM\":50}},{\"duration\":40,\"curve\":[0.5,0,0.5,1],\"color\":{\"aM\":0}},{\"duration\":15,\"curve\":[0.5,0,0.5,1],\"color\":{\"aM\":0}},{\"duration\":15,\"tweenEasing\":0,\"color\":{\"aM\":50}},{\"duration\":10,\"tweenEasing\":null,\"color\":{\"aM\":0}}],\"name\":\"电光\"},{\"frame\":[{\"duration\":46,\"displayIndex\":-1,\"tweenEasing\":null},{\"duration\":104,\"curve\":[0.5,0,0.5,1]},{\"duration\":0,\"curve\":[0.5,0,0.5,1]}],\"name\":\"星光\"},{\"frame\":[{\"duration\":40,\"displayIndex\":-1,\"tweenEasing\":null},{\"duration\":15,\"curve\":[0.5,0,0.5,1],\"color\":{\"aM\":0}},{\"duration\":15,\"tweenEasing\":0,\"color\":{\"aM\":50}},{\"duration\":40,\"curve\":[0.5,0,0.5,1],\"color\":{\"aM\":0}},{\"duration\":15,\"curve\":[0.5,0,0.5,1],\"color\":{\"aM\":0}},{\"duration\":15,\"tweenEasing\":0,\"color\":{\"aM\":50}},{\"duration\":10,\"tweenEasing\":null,\"color\":{\"aM\":0}}],\"name\":\"电光1\"},{\"frame\":[{\"duration\":25,\"curve\":[0.5,0,0.5,1],\"color\":{\"aM\":0}},{\"duration\":15,\"tweenEasing\":0,\"color\":{\"aM\":50}},{\"duration\":40,\"curve\":[0.5,0,0.5,1],\"color\":{\"aM\":0}},{\"duration\":15,\"curve\":[0.5,0,0.5,1],\"color\":{\"aM\":0}},{\"duration\":15,\"tweenEasing\":0,\"color\":{\"aM\":50}},{\"duration\":40,\"tweenEasing\":null,\"color\":{\"aM\":0}}],\"name\":\"电光2\"},{\"frame\":[{\"duration\":24,\"curve\":[0.5,0,0.5,1],\"color\":{\"aM\":0}},{\"duration\":1,\"tweenEasing\":0,\"color\":{\"aM\":50}},{\"duration\":15,\"tweenEasing\":0,\"color\":{\"aM\":70}},{\"duration\":40,\"curve\":[0.5,0,0.5,1],\"color\":{\"aM\":0}},{\"duration\":14,\"curve\":[0.5,0,0.5,1],\"color\":{\"aM\":0}},{\"duration\":1,\"tweenEasing\":0,\"color\":{\"aM\":50}},{\"duration\":15,\"tweenEasing\":0,\"color\":{\"aM\":70}},{\"duration\":40,\"tweenEasing\":null,\"color\":{\"aM\":0}}],\"name\":\"电光21\"},{\"frame\":[{\"duration\":80,\"displayIndex\":-1,\"tweenEasing\":null},{\"duration\":70,\"tweenEasing\":null}],\"name\":\"星光1\"}],\"frame\":[],\"ffd\":[],\"bone\":[{\"frame\":[{\"transform\":{},\"duration\":150}],\"name\":\"root\"},{\"frame\":[{\"transform\":{},\"duration\":150}],\"name\":\"按键\"},{\"frame\":[{\"duration\":40,\"transform\":{}},{\"curve\":[0.5,0,0.5,1],\"transform\":{\"y\":-2.2018,\"x\":1.5573},\"duration\":30},{\"curve\":[0.5,0,0.5,1],\"transform\":{\"y\":28.9332,\"x\":54.9307},\"duration\":40},{\"curve\":[0.5,0,0.5,1],\"transform\":{\"y\":-2.2018,\"x\":1.5573},\"duration\":30},{\"transform\":{\"y\":33.6031,\"x\":61.0949},\"duration\":10}],\"name\":\"电光\"},{\"frame\":[{\"curve\":[0.5,0,0.5,1],\"transform\":{},\"duration\":46,\"tweenRotate\":2},{\"curve\":[0.5,0,0.5,1],\"transform\":{\"skX\":300,\"scY\":2,\"skY\":300,\"scX\":2},\"duration\":20},{\"curve\":[0.5,0,0.5,1],\"transform\":{\"scY\":0.01,\"scX\":0.01},\"duration\":84},{\"transform\":{\"scY\":0.01,\"scX\":0.01},\"duration\":0}],\"name\":\"星光\"},{\"frame\":[{\"duration\":40,\"transform\":{}},{\"curve\":[0.5,0,0.5,1],\"transform\":{},\"duration\":30},{\"curve\":[0.5,0,0.5,1],\"transform\":{\"y\":-22.5362,\"x\":-36.9021},\"duration\":13},{\"tweenEasing\":0,\"transform\":{\"y\":-12.3019,\"x\":-48.5984},\"duration\":27},{\"curve\":[0.5,0,0.5,1],\"transform\":{},\"duration\":30},{\"transform\":{\"y\":-22.5362,\"x\":-36.9021},\"duration\":10}],\"name\":\"电光1\"},{\"frame\":[{\"curve\":[0.5,0,0.5,1],\"transform\":{\"x\":-2.2262},\"duration\":40},{\"curve\":[0.5,0,0.5,1],\"transform\":{\"y\":48.2995,\"x\":-2.2638},\"duration\":40},{\"curve\":[0.5,0,0.5,1],\"transform\":{\"x\":-2.2262},\"duration\":30},{\"transform\":{\"y\":48.2995,\"x\":-2.2638},\"duration\":40}],\"name\":\"电光2\"},{\"frame\":[{\"curve\":[0.5,0,0.5,1],\"transform\":{\"y\":50.8416},\"duration\":40},{\"curve\":[0.5,0,0.5,1],\"transform\":{},\"duration\":40},{\"curve\":[0.5,0,0.5,1],\"transform\":{\"y\":50.8416},\"duration\":30},{\"transform\":{},\"duration\":40}],\"name\":\"电光21\"},{\"frame\":[{\"duration\":80,\"transform\":{}},{\"tweenEasing\":0,\"transform\":{\"y\":2.8024,\"x\":0.5605,\"scY\":1.5,\"scX\":1.5},\"duration\":20,\"tweenRotate\":2},{\"transform\":{\"y\":2.8024,\"x\":0.5605,\"scY\":0.01,\"scX\":0.0595},\"duration\":50,\"tweenRotate\":2}],\"name\":\"星光1\"}],\"name\":\"newAnimation\",\"duration\":150,\"playTimes\":0}],\"ik\":[],\"bone\":[{\"name\":\"root\",\"transform\":{}},{\"transform\":{\"y\":-139.7,\"x\":-2.25},\"name\":\"按键\",\"parent\":\"root\"},{\"length\":47,\"transform\":{\"y\":-64.6,\"x\":-97.9,\"skX\":32.8074,\"skY\":32.8074},\"parent\":\"root\",\"name\":\"电光\"},{\"length\":47,\"transform\":{\"y\":-239.5971,\"x\":54.6127,\"skX\":26.8833,\"skY\":26.8833},\"parent\":\"root\",\"name\":\"电光1\"},{\"length\":47,\"transform\":{\"y\":-181.3574,\"x\":-115.0808,\"skX\":91.1972,\"skY\":91.1972},\"parent\":\"root\",\"name\":\"电光2\"},{\"length\":47,\"transform\":{\"y\":-186.4184,\"x\":116.7057,\"skX\":89.824,\"skY\":89.824},\"parent\":\"root\",\"name\":\"电光21\"},{\"transform\":{\"y\":-63.8458,\"x\":-110.2729},\"name\":\"星光\",\"parent\":\"按键\"},{\"transform\":{\"y\":-100.1947,\"x\":71.3634},\"name\":\"星光1\",\"parent\":\"按键\"}],\"name\":\"armatureName\",\"aabb\":{\"width\":310.30567880385934,\"y\":-278.90982636999445,\"height\":292,\"x\":-154.2256862145826}}],\"name\":\"chuangjianyouxi\",\"version\":\"4.0\",\"isGlobal\":0}"
}